CHANGES.txt
LICENSE.txt
MANIFEST.in
README.txt
setup.py
Pizza.py.egg-info/PKG-INFO
Pizza.py.egg-info/SOURCES.txt
Pizza.py.egg-info/dependency_links.txt
Pizza.py.egg-info/requires.txt
Pizza.py.egg-info/top_level.txt
bin/angle_distribute.py
bin/block.py
bin/bond_distribute.py
bin/clogview.py
bin/cluster.py
bin/density.py
bin/density2d.py
bin/density_area.py
bin/distance.py
bin/dview.py
bin/dview_standalone.py
bin/flux.py
bin/iview.py
bin/logview.py
bin/movie.py
bin/plot.py
docs/Manual.html
docs/Manual.pdf
docs/Manual.txt
docs/Section_basics.html
docs/Section_basics.txt
docs/Section_examples.html
docs/Section_examples.txt
docs/Section_extend.html
docs/Section_extend.txt
docs/Section_install.html
docs/Section_install.txt
docs/Section_intro.html
docs/Section_intro.txt
docs/Section_tools.html
docs/Section_tools.txt
docs/animate.html
docs/animate.txt
docs/bdump.html
docs/bdump.txt
docs/cdata.html
docs/cdata.txt
docs/cfg.html
docs/cfg.txt
docs/chain.html
docs/chain.txt
docs/clog.html
docs/clog.txt
docs/data.html
docs/data.txt
docs/dump.html
docs/dump.txt
docs/ensight.html
docs/ensight.txt
docs/gl.html
docs/gl.txt
docs/gnu.html
docs/gnu.txt
docs/histo.html
docs/histo.txt
docs/image.html
docs/image.txt
docs/ldump.html
docs/ldump.txt
docs/log.html
docs/log.txt
docs/matlab.html
docs/matlab.txt
docs/mdump.html
docs/mdump.txt
docs/pair.html
docs/pair.txt
docs/patch.html
docs/patch.txt
docs/pdbfile.html
docs/pdbfile.txt
docs/plotview.html
docs/plotview.txt
docs/rasmol.html
docs/rasmol.txt
docs/raster.html
docs/raster.txt
docs/svg.html
docs/svg.txt
docs/tdump.html
docs/tdump.txt
docs/tools.jpg
docs/vcr.html
docs/vcr.txt
docs/vec.html
docs/vec.txt
docs/vmd.html
docs/vmd.txt
docs/vtk.html
docs/vtk.txt
docs/xyz.html
docs/xyz.txt
pizza/DEFAULTS.py
pizza/__init__.py
pizza/animate.py
pizza/bdump.py
pizza/cdata.py
pizza/cfg.py
pizza/chain.py
pizza/clog.py
pizza/data.py
pizza/dump.py
pizza/ensight.py
pizza/gl.py
pizza/gnu.py
pizza/histo.py
pizza/image.py
pizza/ldump.py
pizza/log.py
pizza/matlab.py
pizza/mdump.py
pizza/pair.py
pizza/patch.py
pizza/pdbfile.py
pizza/pizza.py
pizza/plotview.py
pizza/rasmol.py
pizza/raster.py
pizza/svg.py
