Metadata-Version: 1.0
Name: Pizza.py
Version: 0.1.0
Summary: Tools for working with the LAMMPS molecular dynamics package
Home-page: http://pypi.python.org/pypi/Pizza.py/
Author: Steve Plimpton
Author-email: sjplimp@sandia.gov
License: LICENSE.txt
Platform: UNKNOWN
